danceir/__init__.py
danceir/cli.py
danceir/analysis/__init__.py
danceir/analysis/tempo.py
danceir/config/__init__.py
danceir/config/body_model.py
danceir/config/defaults.py
danceir/evaluation/__init__.py
danceir/evaluation/metrics.py
danceir/features/__init__.py
danceir/features/anchors.py
danceir/features/center_of_mass.py
danceir/features/energy.py
danceir/io/__init__.py
danceir/io/anchor_io.py
danceir/io/keypoint_loader.py
danceir/io/path_manager.py
danceir/pipelines/__init__.py
danceir/pipelines/tempo_estimation.py
danceir/preprocessing/__init__.py
danceir/preprocessing/filtering.py
danceir/preprocessing/normalization.py
danceir/preprocessing/signal_processing.py
danceir/utils/__init__.py
danceir/utils/exceptions.py
danceir-1.0.0.dist-info/licenses/LICENSE
demo/Demo.ipynb
demo/extract_2dpose.py
tests/__init__.py
tests/test_evaluation.py
tests/test_features.py
tests/test_io.py
tests/test_pipelines.py
danceir-1.0.0.dist-info/METADATA
danceir-1.0.0.dist-info/WHEEL
danceir-1.0.0.dist-info/entry_points.txt
danceir-1.0.0.dist-info/top_level.txt
danceir-1.0.0.dist-info/RECORD
