Metadata-Version: 2.4
Name: danceir
Version: 1.0.0
Summary: A modular toolbox for dance motion analysis, feature extraction, and tempo estimation
Author-email: Sagar Dutta <sagar0dutta@gmail.com>
License-Expression: MIT
Project-URL: Homepage, https://sagar0dutta.github.io/danceir
Project-URL: Documentation, https://sagar0dutta.github.io/danceir
Project-URL: Repository, https://github.com/sagar0dutta/danceir
Project-URL: Issues, https://github.com/sagar0dutta/danceir/issues
Keywords: dance,motion-analysis,tempo-estimation,keypoints
Classifier: Development Status :: 3 - Alpha
Classifier: Intended Audience :: Science/Research
Classifier: Programming Language :: Python :: 3
Classifier: Programming Language :: Python :: 3.8
Classifier: Programming Language :: Python :: 3.9
Classifier: Programming Language :: Python :: 3.10
Classifier: Programming Language :: Python :: 3.11
Classifier: Programming Language :: Python :: 3.12
Requires-Python: >=3.8
License-File: LICENSE
Requires-Dist: numpy>=1.20.0
Requires-Dist: scipy>=1.7.0
Requires-Dist: librosa>=0.9.0
Provides-Extra: demo
Requires-Dist: matplotlib>=3.5; extra == "demo"
Requires-Dist: opencv-python>=4.7; extra == "demo"
Requires-Dist: mediapipe>=0.10; extra == "demo"
Provides-Extra: dev
Requires-Dist: pytest>=7.0; extra == "dev"
Requires-Dist: pytest-cov>=3.0; extra == "dev"
Dynamic: license-file
